pipe_fn.py
test.py
pipe_fn/__init__.py
pipe_fn-0.2.2.dist-info/DESCRIPTION.rst
pipe_fn-0.2.2.dist-info/METADATA
pipe_fn-0.2.2.dist-info/RECORD
pipe_fn-0.2.2.dist-info/WHEEL
pipe_fn-0.2.2.dist-info/metadata.json
pipe_fn-0.2.2.dist-info/top_level.txt
