Metadata-Version: 2.0
Name: pipe-fn
Version: 0.2.2
Summary: functional pipeline operation in Python
Home-page: https://github.com/Xython/pipe-fn
Author: thautwarm
Author-email: twshere@outlook.com
License: MIT
Platform: any
Classifier: Programming Language :: Python :: 3.4
Classifier: Programming Language :: Python :: 3.5
Classifier: Programming Language :: Python :: 3.6
Classifier: Programming Language :: Python :: 3.7
Classifier: Programming Language :: Python :: Implementation :: CPython
